odoo/addons/product_category_uom/README.rst
odoo/addons/product_category_uom/__init__.py
odoo/addons/product_category_uom/__manifest__.py
odoo/addons/product_category_uom/i18n/it.po
odoo/addons/product_category_uom/i18n/product_category_uom.pot
odoo/addons/product_category_uom/models/__init__.py
odoo/addons/product_category_uom/models/product_category.py
odoo/addons/product_category_uom/models/product_template.py
odoo/addons/product_category_uom/readme/CONTRIBUTORS.md
odoo/addons/product_category_uom/readme/DESCRIPTION.md
odoo/addons/product_category_uom/static/description/icon.png
odoo/addons/product_category_uom/static/description/index.html
odoo/addons/product_category_uom/tests/__init__.py
odoo/addons/product_category_uom/tests/test_product_category_uom.py
odoo/addons/product_category_uom/views/product_category.xml
odoo_addon_product_category_uom-18.0.1.0.0.4.dist-info/METADATA
odoo_addon_product_category_uom-18.0.1.0.0.4.dist-info/WHEEL
odoo_addon_product_category_uom-18.0.1.0.0.4.dist-info/top_level.txt
odoo_addon_product_category_uom-18.0.1.0.0.4.dist-info/RECORD
