Metadata-Version: 2.1
Name: odoo-addon-product_category_uom
Version: 18.0.1.0.0.4
Requires-Python: >=3.10
Requires-Dist: odoo==18.0.*
Summary: Define default product UoM at product category level
Home-page: https://github.com/OCA/product-attribute
License: AGPL-3
Author: ForgeFlow,Odoo Community Association (OCA)
Author-email: support@odoo-community.org
Classifier: Programming Language :: Python
Classifier: Framework :: Odoo
Classifier: Framework :: Odoo :: 18.0
Classifier: License :: OSI Approved :: GNU Affero General Public License v3
